lm_cli/__init__.py
lm_cli/auth.py
lm_cli/config.py
lm_cli/constants.py
lm_cli/exceptions.py
lm_cli/logs.py
lm_cli/main.py
lm_cli/render.py
lm_cli/requests.py
lm_cli/schemas.py
lm_cli/subapps/__init__.py
lm_cli/subapps/bookings.py
lm_cli/subapps/configurations.py
lm_cli/subapps/features.py
lm_cli/subapps/jobs.py
lm_cli/subapps/license_servers.py
lm_cli/subapps/products.py
lm_cli/text_tools.py
lm_cli/time_loop.py
license_manager_cli-4.5.0.dist-info/METADATA
license_manager_cli-4.5.0.dist-info/WHEEL
license_manager_cli-4.5.0.dist-info/entry_points.txt
license_manager_cli-4.5.0.dist-info/licenses/LICENSE
license_manager_cli-4.5.0.dist-info/RECORD
