Metadata-Version: 2.4
Name: license-manager-cli
Version: 4.5.0
Summary: License Manager CLI Client
License: MIT
License-File: LICENSE
Author: Omnivector Solutions
Author-email: info@omnivector.solutions
Requires-Python: >=3.12,<4.0
Classifier: License :: OSI Approved :: MIT License
Classifier: Programming Language :: Python :: 3
Classifier: Programming Language :: Python :: 3.12
Classifier: Programming Language :: Python :: 3.13
Classifier: Programming Language :: Python :: 3.14
Requires-Dist: httpx (>=0.28.1,<0.29.0)
Requires-Dist: importlib-metadata (<5.0)
Requires-Dist: loguru (>=0.7.3,<0.8.0)
Requires-Dist: pendulum (==3.1.0)
Requires-Dist: py-buzz (>=7.3.0,<8.0.0)
Requires-Dist: pydantic (>=2.12,<3.0)
Requires-Dist: pydantic-settings (>=2.11.0,<3.0.0)
Requires-Dist: pyperclip (>=1.11.0,<2.0.0)
Requires-Dist: python-dotenv (>=1.1.1,<2.0.0)
Requires-Dist: python-jose (>=3.5.0,<4.0.0)
Requires-Dist: rich (>=14.2.0,<15.0.0)
Requires-Dist: typer (>=0.19.2,<0.20.0)
Project-URL: Documentation, https://omnivector-solutions.github.io/license-manager/
Project-URL: Repository, https://github.com/omnivector-solutions/license-manager
